{
	"forms": {
		"Output_LB": {
			"timeStamp": "2024-01-22T03:32:34Z"
		},
		"Scour Report - Summary": {
			"timeStamp": "2024-01-22T03:32:34Z",
			"destination": "detailPrinter"
		},
		"Scour Report - State": {
			"timeStamp": "2024-01-22T03:32:34Z",
			"destination": "detailPrinter"
		},
		"I_ScourReport": {
			"timeStamp": "2024-01-22T03:32:34Z"
		},
		"Output": {
			"timeStamp": "2024-01-22T03:32:34Z",
			"destination": "listScreen"
		},
		"Scour Report - Mass": {
			"timeStamp": "2024-01-22T03:32:34Z",
			"destination": "detailPrinter"
		},
		"Scour Report - Agencies": {
			"timeStamp": "2024-01-22T03:32:34Z",
			"destination": "detailPrinter"
		}
	}
}